tools/__init__.py
tools/array.py
tools/data.py
tools/dict_operations.py
tools/exp.py
tools/modules.py
tools/os.py
tools/random.py
tools/tools.py
tools/hydra/__init__.py
tools/numpy/__init__.py
tools/numpy/_f.py
tools/numpy/_utils.py
tools/pandas/__init__.py
tools/plot/__init__.py
tools/plot/sklearn.py
tools/plot/utils.py
tools/sklearn/__init__.py
tools/sklearn/metrics.py
tools/sklearn/model_selection.py
tools/sklearn/preprocessing.py
tools/stats/__init__.py
tools/torch/__init__.py
tools/torch/_pandas.py
tools/torch/data.py
tools/torch/estimator.py
tools/torch/federated_learning.py
tools/torch/layers.py
tools/torch/model.py
tools/torch/plot.py
tools/torch/utils.py
tools/torch/optim/__init__.py
tools/torch/optim/lr_scheduler.py
tools-1.0.17.dist-info/LICENSE.txt
tools-1.0.17.dist-info/METADATA
tools-1.0.17.dist-info/WHEEL
tools-1.0.17.dist-info/top_level.txt
tools-1.0.17.dist-info/RECORD
