Metadata-Version: 2.1
Name: tools
Version: 1.0.17
Summary: python syntax tool
Home-page: https://github.com/jsyoo61/tools
Author: JaeSung Yoo
Author-email: jsyoo61@unc.edu
Classifier: Programming Language :: Python :: 3
Classifier: License :: OSI Approved :: MIT License
Classifier: Operating System :: OS Independent
Requires-Python: >=3.6
License-File: LICENSE.txt
